extents/__init__.py
extents/extents.py
extents-0.2.2.dist-info/LICENSE
extents-0.2.2.dist-info/METADATA
extents-0.2.2.dist-info/WHEEL
extents-0.2.2.dist-info/top_level.txt
extents-0.2.2.dist-info/RECORD
