Metadata-Version: 2.1
Name: extents
Version: 0.2.2
Summary: An intervals library implemented in pure python, meant to be a drop-in replacment for the pyinterval library.
Author-email: Michael Frank <michaelfrank@swapp.ai>
Maintainer-email: Michael Frank <michaelfrank@swapp.ai>
License: MIT License
Project-URL: Homepage, https://github.com/swapp-ai/extents
Project-URL: Documentation, https://github.com/swapp-ai/extents/blob/main/README.md
Project-URL: Repository, https://github.com/swapp-ai/extents.git
Project-URL: Issues, https://github.com/swapp-ai/extents/issues
Keywords: interval,intervals
Classifier: Programming Language :: Python
Requires-Python: >=3.7
License-File: LICENSE
Provides-Extra: dev
Requires-Dist: pytest ; extra == 'dev'
Requires-Dist: pytest-cov ; extra == 'dev'
Requires-Dist: tomlkit ; extra == 'dev'
Requires-Dist: jupyter ; extra == 'dev'
Requires-Dist: myst-nb ; extra == 'dev'
Requires-Dist: sphinx-autoapi ; extra == 'dev'
Requires-Dist: sphinx-rtd-theme ; extra == 'dev'
Requires-Dist: sphinx-markdown-builder ; extra == 'dev'
Provides-Extra: doc
Requires-Dist: jupyter ; extra == 'doc'
Requires-Dist: myst-nb ; extra == 'doc'
Requires-Dist: sphinx-autoapi ; extra == 'doc'
Requires-Dist: sphinx-rtd-theme ; extra == 'doc'
Requires-Dist: sphinx-markdown-builder ; extra == 'doc'
Provides-Extra: tests
Requires-Dist: pytest ; extra == 'tests'
